{"name":"iSpoiler","tagline":"Mac os X Spoiler Downloader Tool","body":"iSpoiler\r\n========\r\n\r\n[![Flattr this git repo](http://api.flattr.com/button/flattr-badge-large.png)](https://flattr.com/submit/auto?user_id=YaGeek&url=https://github.com/yageek/iSpoiler&title=iSpoiler&language=&tags=github&category=software)\r\n\r\nMac OS X spoiler downloader tool for geocaching.com.\r\n\r\n## Download\r\nBintray : [Last release (1.2)](http://dl.bintray.com/yageek/iSpoiler/iSpoiler1.2.dmg)\r\n","google":"","note":"Don't delete this file! It's used internally to help with page regeneration."}